brigid/__init__.py
brigid/api/__init__.py
brigid/api/default_translations.py
brigid/api/http_handlers.py
brigid/api/middlewares.py
brigid/api/renderers.py
brigid/api/settings.py
brigid/api/sitemaps.py
brigid/api/static_cache.py
brigid/api/tests/__init__.py
brigid/api/tests/test_http_handlers.py
brigid/api/utils.py
brigid/application/__init__.py
brigid/application/application.py
brigid/application/settings.py
brigid/cli/__init__.py
brigid/cli/__main__.py
brigid/cli/application.py
brigid/cli/commands/__init__.py
brigid/cli/commands/configs.py
brigid/cli/commands/static.py
brigid/cli/commands/templates.py
brigid/cli/commands/validate.py
brigid/conftest.py
brigid/core/__init__.py
brigid/core/api.py
brigid/core/entities.py
brigid/core/errors.py
brigid/core/logging.py
brigid/core/sentry.py
brigid/core/settings.py
brigid/core/utils.py
brigid/domain/__init__.py
brigid/domain/entities.py
brigid/domain/html.py
brigid/domain/request_context.py
brigid/domain/tests/__init__.py
brigid/domain/tests/test_html.py
brigid/domain/tests/test_text.py
brigid/domain/tests/test_urls.py
brigid/domain/text.py
brigid/domain/urls.py
brigid/jinja2_render/__init__.py
brigid/jinja2_render/entities.py
brigid/jinja2_render/jinjaglobals.py
brigid/jinja2_render/settings.py
brigid/jinja2_render/templates.py
brigid/jinja2_render/tests/__init__.py
brigid/jinja2_render/tests/test_templates.py
brigid/jinja2_render/utils.py
brigid/library/__init__.py
brigid/library/connectivity.py
brigid/library/discovering.py
brigid/library/entities.py
brigid/library/series.py
brigid/library/settings.py
brigid/library/similarity.py
brigid/library/storage.py
brigid/library/tests/__init__.py
brigid/library/tests/make.py
brigid/library/tests/test_entities.py
brigid/library/utils.py
brigid/markdown_render/__init__.py
brigid/markdown_render/context.py
brigid/markdown_render/markdown_render.py
brigid/markdown_render/processors/__init__.py
brigid/markdown_render/processors/collection_block.py
brigid-0.15.0.dist-info/METADATA
brigid-0.15.0.dist-info/WHEEL
brigid-0.15.0.dist-info/entry_points.txt
brigid-0.15.0.dist-info/licenses/LICENSE
brigid-0.15.0.dist-info/RECORD
