Metadata-Version: 2.4
Name: brigid
Version: 0.15.0
Summary: Static site generator.
License: BSD-3-Clause
License-File: LICENSE
Keywords: blog,blog-engine,site,markdown,cms,content management system,personal site
Author: Aliaksei Yaletski (Tiendil)
Author-email: a.eletsky@gmail.com
Requires-Python: >=3.12,<4.0
Classifier: Environment :: Web Environment
Classifier: Framework :: AsyncIO
Classifier: Framework :: FastAPI
Classifier: Intended Audience :: Developers
Classifier: Intended Audience :: End Users/Desktop
Classifier: License :: OSI Approved :: BSD License
Classifier: Natural Language :: English
Classifier: Operating System :: OS Independent
Classifier: Programming Language :: Python :: 3
Classifier: Programming Language :: Python :: 3.12
Classifier: Programming Language :: Python :: 3.13
Classifier: Programming Language :: Python :: 3.14
Classifier: Programming Language :: Python :: 3 :: Only
Classifier: Programming Language :: Python :: Implementation :: CPython
Classifier: Topic :: Internet :: WWW/HTTP
Classifier: Topic :: Internet :: WWW/HTTP :: Dynamic Content
Classifier: Topic :: Internet :: WWW/HTTP :: Dynamic Content :: News/Diary
Classifier: Topic :: Internet :: WWW/HTTP :: HTTP Servers
Classifier: Topic :: Internet :: WWW/HTTP :: WSGI :: Application
Classifier: Topic :: Internet :: WWW/HTTP :: WSGI :: Server
Classifier: Topic :: Office/Business :: News/Diary
Classifier: Topic :: Text Processing :: Markup
Classifier: Topic :: Text Processing :: Markup :: HTML
Classifier: Topic :: Text Processing :: Markup :: Markdown
Requires-Dist: beautifulsoup4 (==4.13.*)
Requires-Dist: fastapi (==0.121.*)
Requires-Dist: fastmcp (==2.13.*)
Requires-Dist: feedgenerator (==2.2.*)
Requires-Dist: html5lib (==1.1.*)
Requires-Dist: jinja2 (==3.1.*)
Requires-Dist: markdown (==3.9.*)
Requires-Dist: pillow (==11.3.*)
Requires-Dist: pydantic (==2.12.*)
Requires-Dist: pydantic-settings (==2.11.*)
Requires-Dist: pymdown-extensions (==10.16.*)
Requires-Dist: python-frontmatter (==1.1.*)
Requires-Dist: sentry-sdk (==2.37.*)
Requires-Dist: structlog (==25.4.*)
Requires-Dist: toml (==0.10.*)
Requires-Dist: typer (==0.17.*)
Project-URL: Repository, https://github.com/Tiendil/brigid
